README.md
setup.py
urtoday/__init__.py
urtoday/main.py
urtoday/overview.py
urtoday/urtutils.py
urtoday.egg-info/PKG-INFO
urtoday.egg-info/SOURCES.txt
urtoday.egg-info/dependency_links.txt
urtoday.egg-info/entry_points.txt
urtoday.egg-info/top_level.txt