Metadata-Version: 2.1
Name: urtoday
Version: 1.0
Summary: URtoday
Home-page: https://github.com/poyynt/urtoday/
Author: Parsa Torbati
Author-email: parsa@programmer.net
License: UNKNOWN
Platform: UNKNOWN
Classifier: Programming Language :: Python :: 3
Classifier: License :: OSI Approved :: Apple Public Source License
Classifier: Operating System :: OS Independent
Classifier: Development Status :: 5 - Production/Stable
Classifier: Natural Language :: English
Classifier: Topic :: Utilities
Requires-Python: >=3.2
